Metadata-Version: 1.1
Name: flist
Version: 0.7
Summary: File List Expansion
Home-page: https://github.com/avnr/flist
Author: Avner Herskovits
Author-email: avnr_ at outlook.com
License: UNKNOWN
Download-URL: https://github.com/avnr/flist/tarball/0.602
Platform: UNKNOWN
Classifier: Development Status :: 4 - Beta
Classifier: Environment :: Console
Classifier: Environment :: No Input/Output (Daemon)
Classifier: Environment :: Other Environment
Classifier: Intended Audience :: Developers
Classifier: Intended Audience :: Information Technology
Classifier: Intended Audience :: System Administrators
Classifier: License :: OSI Approved :: MIT License
Classifier: Operating System :: OS Independent
Classifier: Programming Language :: Python
Classifier: Topic :: System :: Filesystems
Classifier: Topic :: Utilities
